openai_chat_thread.py
openai_chat_thread-1.1.1.dist-info/METADATA
openai_chat_thread-1.1.1.dist-info/WHEEL
openai_chat_thread-1.1.1.dist-info/entry_points.txt
openai_chat_thread-1.1.1.dist-info/top_level.txt
openai_chat_thread-1.1.1.dist-info/RECORD
