Metadata-Version: 2.1
Name: openai-chat-thread
Version: 1.1.1
Summary: UNKNOWN
Home-page: UNKNOWN
License: UNKNOWN
Platform: UNKNOWN
Requires-Dist: openai
Requires-Dist: python-dotenv
Requires-Dist: opencc-python-reimplemented
